alphastats/__init__.py
alphastats/cli.py
alphastats/data/contaminations.txt
alphastats/dataset/__init__.py
alphastats/dataset/dataset.py
alphastats/dataset/factory.py
alphastats/dataset/harmonizer.py
alphastats/dataset/id_holder.py
alphastats/dataset/keys.py
alphastats/dataset/pathway.py
alphastats/dataset/plotting.py
alphastats/dataset/preprocessing.py
alphastats/dataset/statistics.py
alphastats/dataset/utils.py
alphastats/gui/AlphaPeptStats.py
alphastats/gui/__init__.py
alphastats/gui/alphapeptstats_logo.png
alphastats/gui/alphastats_logo.png
alphastats/gui/alphastats_logo_2.png
alphastats/gui/gui.py
alphastats/gui/requirements.txt
alphastats/gui/.streamlit/config.toml
alphastats/gui/example_data/metadata.xlsx
alphastats/gui/example_data/proteinGroups.txt
alphastats/gui/pages_/01_Home.py
alphastats/gui/pages_/02_Import Data.py
alphastats/gui/pages_/03_Data Overview.py
alphastats/gui/pages_/04_Preprocessing.py
alphastats/gui/pages_/05_Analysis.py
alphastats/gui/pages_/06_LLM.py
alphastats/gui/pages_/07_Results.py
alphastats/gui/pages_/08_Upload Custom Analysis.py
alphastats/gui/pages_/__init__.py
alphastats/gui/utils/__init__.py
alphastats/gui/utils/analysis.py
alphastats/gui/utils/analysis_helper.py
alphastats/gui/utils/import_helper.py
alphastats/gui/utils/llm_helper.py
alphastats/gui/utils/options.py
alphastats/gui/utils/overview_helper.py
alphastats/gui/utils/preprocessing_helper.py
alphastats/gui/utils/result.py
alphastats/gui/utils/session_manager.py
alphastats/gui/utils/state_keys.py
alphastats/gui/utils/state_utils.py
alphastats/gui/utils/ui_helper.py
alphastats/gui/utils/upload_custom_analysis.py
alphastats/llm/__init__.py
alphastats/llm/enrichment_analysis.py
alphastats/llm/llm_functions.py
alphastats/llm/llm_integration.py
alphastats/llm/llm_utils.py
alphastats/llm/prompts.py
alphastats/llm/uniprot_utils.py
alphastats/loader/__init__.py
alphastats/loader/alphapept_loader.py
alphastats/loader/base_loader.py
alphastats/loader/diann_loader.py
alphastats-0.7.2.dist-info/licenses/LICENSE.txt
alphastats-0.7.2.dist-info/METADATA
alphastats-0.7.2.dist-info/WHEEL
alphastats-0.7.2.dist-info/entry_points.txt
alphastats-0.7.2.dist-info/top_level.txt
alphastats-0.7.2.dist-info/RECORD
