Metadata-Version: 2.4
Name: alphastats
Version: 0.7.2
Summary: An open-source Python package for automated and scalable statistical analysis of mass spectrometry-based proteomics
Author-email: Mann Labs <elena.krismer@gmail.com>
License: Apache
Project-URL: Homepage, https://github.com/MannLabs/alphastats
Project-URL: Documentation, https://mannlabs.github.io/alphapeptstats/
Project-URL: Source, https://github.com/MannLabs/alphastats
Project-URL: PyPi, https://pypi.org/project/alphastats/
Keywords: bioinformatics,software,mass spectrometry,proteomics
Classifier: Development Status :: 4 - Beta
Classifier: Intended Audience :: Science/Research
Classifier: License :: OSI Approved :: Apache Software License
Classifier: Operating System :: OS Independent
Classifier: Programming Language :: Python :: 3
Classifier: Programming Language :: Python :: 3.9
Classifier: Programming Language :: Python :: 3.10
Classifier: Programming Language :: Python :: 3.11
Classifier: Topic :: Scientific/Engineering :: Bio-Informatics
Requires-Python: <4,>=3.9
License-File: LICENSE.txt
Requires-Dist: anndata==0.9.1
Requires-Dist: combat==0.3.3
Requires-Dist: diffxpy==0.7.4
Requires-Dist: gprofiler-official==1.0.0
Requires-Dist: kaleido==0.2.1
Requires-Dist: litellm==1.72.0
Requires-Dist: eval_type_backport==0.2.2
Requires-Dist: numba-stats==0.5.0
Requires-Dist: numba==0.57.0
Requires-Dist: numpy==1.23.5
Requires-Dist: ollama==0.3.3
Requires-Dist: openai==1.83.0
Requires-Dist: openpyxl>=3.0.10
Requires-Dist: pandas==2.0.2
Requires-Dist: pingouin==0.5.3
Requires-Dist: plotly==5.15.0
Requires-Dist: pyteomics==4.6.0
Requires-Dist: scikit-learn==1.2.2
Requires-Dist: scipy==1.10.1
Requires-Dist: sklearn_pandas==2.2.0
Requires-Dist: statsmodels==0.14.0
Requires-Dist: streamlit==1.45.1
Requires-Dist: swifter==1.2.0
Requires-Dist: tables==3.7.0
Requires-Dist: tqdm>=4.64.0
Requires-Dist: umap-learn==0.5.3
Requires-Dist: xlsxwriter==3.1.0
Requires-Dist: st_cytoscape==0.0.5
Requires-Dist: stqdm==0.0.5
Requires-Dist: tiktoken>=0.7.0
Requires-Dist: click==8.0.1; python_version == "3.10"
Requires-Dist: data_cache>=0.1.6; python_version == "3.10"
Requires-Dist: nbformat>=5.0; python_version == "3.10"
Dynamic: license-file
